{
  "$schema": "http://schema.management.azure.com/schemas/2015-01-01/deploymentParameters.json#",
  "contentVersion": "1.0.0.0",
  "parameters": {
    "input": {
      "value": {
        "Id": "/providers/Microsoft.Management/managementGroups/5318a58c-110f-4cf3-b21b-e9c1ca7c71ff",
        "Type": "/providers/Microsoft.Management/managementGroups",
        "Name": "5318a58c-110f-4cf3-b21b-e9c1ca7c71ff",
        "TenantId": "5318a58c-110f-4cf3-b21b-e9c1ca7c71ff",
        "DisplayName": "Tenant Root Group",
        "UpdatedTime": "0001-01-01T00:00:00Z",
        "UpdatedBy": null,
        "ParentId": null,
        "ParentName": null,
        "ParentDisplayName": null,
        "Children": [
          {
            "Type": "/providers/Microsoft.Management/managementGroups",
            "Id": "/providers/Microsoft.Management/managementGroups/kr",
            "Name": "kr",
            "DisplayName": "kr",
            "Children": [
              {
                "Type": "/providers/Microsoft.Management/managementGroups",
                "Id": "/providers/Microsoft.Management/managementGroups/kr-decomissioned",
                "Name": "kr-decomissioned",
                "DisplayName": "decommissioned",
                "Children": null
              },
              {
                "Type": "/providers/Microsoft.Management/managementGroups",
                "Id": "/providers/Microsoft.Management/managementGroups/kr-sandboxes",
                "Name": "kr-sandboxes",
                "DisplayName": "sandboxes",
                "Children": null
              },
              {
                "Type": "/providers/Microsoft.Management/managementGroups",
                "Id": "/providers/Microsoft.Management/managementGroups/kr-platform",
                "Name": "kr-platform",
                "DisplayName": "platform",
                "Children": [
                  {
                    "Type": "/providers/Microsoft.Management/managementGroups",
                    "Id": "/providers/Microsoft.Management/managementGroups/kr-identity",
                    "Name": "kr-identity",
                    "DisplayName": "identity",
                    "Children": null
                  },
                  {
                    "Type": "/providers/Microsoft.Management/managementGroups",
                    "Id": "/providers/Microsoft.Management/managementGroups/kr-management",
                    "Name": "kr-management",
                    "DisplayName": "management",
                    "Children": [
                      {
                        "Type": "/subscriptions",
                        "Id": "/subscriptions/7a93a5e4-9e66-4b0c-a5a7-26c3cd02892b",
                        "Name": "7a93a5e4-9e66-4b0c-a5a7-26c3cd02892b",
                        "DisplayName": "KEROWLAN-ES-Management",
                        "Children": null
                      }
                    ]
                  },
                  {
                    "Type": "/providers/Microsoft.Management/managementGroups",
                    "Id": "/providers/Microsoft.Management/managementGroups/kr-connectivity",
                    "Name": "kr-connectivity",
                    "DisplayName": "connectivity",
                    "Children": null
                  }
                ]
              },
              {
                "Type": "/providers/Microsoft.Management/managementGroups",
                "Id": "/providers/Microsoft.Management/managementGroups/kr-landingzones",
                "Name": "kr-landingzones",
                "DisplayName": "Landing Zones",
                "Children": [
                  {
                    "Type": "/providers/Microsoft.Management/managementGroups",
                    "Id": "/providers/Microsoft.Management/managementGroups/kr-online",
                    "Name": "kr-online",
                    "DisplayName": "online",
                    "Children": null
                  },
                  {
                    "Type": "/providers/Microsoft.Management/managementGroups",
                    "Id": "/providers/Microsoft.Management/managementGroups/kr-corp",
                    "Name": "kr-corp",
                    "DisplayName": "corp",
                    "Children": null
                  },
                  {
                    "Type": "/providers/Microsoft.Management/managementGroups",
                    "Id": "/providers/Microsoft.Management/managementGroups/kr-sap",
                    "Name": "kr-sap",
                    "DisplayName": "sap",
                    "Children": null
                  }
                ]
              }
            ]
          },
          {
            "Type": "/providers/Microsoft.Management/managementGroups",
            "Id": "/providers/Microsoft.Management/managementGroups/tf",
            "Name": "tf",
            "DisplayName": "ES Terraform Testing",
            "Children": [
              {
                "Type": "/providers/Microsoft.Management/managementGroups",
                "Id": "/providers/Microsoft.Management/managementGroups/tf-decommissioned",
                "Name": "tf-decommissioned",
                "DisplayName": "Decommissioned",
                "Children": null
              },
              {
                "Type": "/providers/Microsoft.Management/managementGroups",
                "Id": "/providers/Microsoft.Management/managementGroups/tf-landing-zones",
                "Name": "tf-landing-zones",
                "DisplayName": "Landing Zones",
                "Children": [
                  {
                    "Type": "/providers/Microsoft.Management/managementGroups",
                    "Id": "/providers/Microsoft.Management/managementGroups/customer-web-prod",
                    "Name": "customer-web-prod",
                    "DisplayName": "Prod Web Applications",
                    "Children": null
                  },
                  {
                    "Type": "/providers/Microsoft.Management/managementGroups",
                    "Id": "/providers/Microsoft.Management/managementGroups/customer-web-test",
                    "Name": "customer-web-test",
                    "DisplayName": "Test Web Applications",
                    "Children": null
                  },
                  {
                    "Type": "/providers/Microsoft.Management/managementGroups",
                    "Id": "/providers/Microsoft.Management/managementGroups/customer-corp",
                    "Name": "customer-corp",
                    "DisplayName": "Corp Custom",
                    "Children": null
                  },
                  {
                    "Type": "/providers/Microsoft.Management/managementGroups",
                    "Id": "/providers/Microsoft.Management/managementGroups/customer-sap",
                    "Name": "customer-sap",
                    "DisplayName": "SAP",
                    "Children": null
                  },
                  {
                    "Type": "/providers/Microsoft.Management/managementGroups",
                    "Id": "/providers/Microsoft.Management/managementGroups/customer-online",
                    "Name": "customer-online",
                    "DisplayName": "Online",
                    "Children": null
                  },
                  {
                    "Type": "/providers/Microsoft.Management/managementGroups",
                    "Id": "/providers/Microsoft.Management/managementGroups/customer-web-dev",
                    "Name": "customer-web-dev",
                    "DisplayName": "Dev Web Applications",
                    "Children": null
                  },
                  {
                    "Type": "/providers/Microsoft.Management/managementGroups",
                    "Id": "/providers/Microsoft.Management/managementGroups/self-serv-lz1",
                    "Name": "self-serv-lz1",
                    "DisplayName": "Self Serve LZ1",
                    "Children": null
                  }
                ]
              },
              {
                "Type": "/providers/Microsoft.Management/managementGroups",
                "Id": "/providers/Microsoft.Management/managementGroups/tf-sandboxes",
                "Name": "tf-sandboxes",
                "DisplayName": "Sandboxes",
                "Children": null
              },
              {
                "Type": "/providers/Microsoft.Management/managementGroups",
                "Id": "/providers/Microsoft.Management/managementGroups/tf-platform",
                "Name": "tf-platform",
                "DisplayName": "Platform",
                "Children": [
                  {
                    "Type": "/providers/Microsoft.Management/managementGroups",
                    "Id": "/providers/Microsoft.Management/managementGroups/tf-identity",
                    "Name": "tf-identity",
                    "DisplayName": "Identity",
                    "Children": null
                  },
                  {
                    "Type": "/providers/Microsoft.Management/managementGroups",
                    "Id": "/providers/Microsoft.Management/managementGroups/tf-management",
                    "Name": "tf-management",
                    "DisplayName": "Management",
                    "Children": null
                  },
                  {
                    "Type": "/providers/Microsoft.Management/managementGroups",
                    "Id": "/providers/Microsoft.Management/managementGroups/tf-connectivity",
                    "Name": "tf-connectivity",
                    "DisplayName": "Connectivity",
                    "Children": null
                  }
                ]
              }
            ]
          }
        ],
        "properties": {
          "policyDefinitions": [],
          "policySetDefinitions": [],
          "policyAssignments": [],
          "roleDefinitions": [],
          "roleAssignments": []
        }
      }
    }
  }
}
